ratecurve/__init__.py
ratecurve/__main__.py
ratecurve/equations.py
ratecurve/ratecurve.py
ratecurve/utils.py
ratecurve-0.0.4.dist-info/LICENSE
ratecurve-0.0.4.dist-info/METADATA
ratecurve-0.0.4.dist-info/WHEEL
ratecurve-0.0.4.dist-info/top_level.txt
ratecurve-0.0.4.dist-info/RECORD
